[{"Fiscal Year":"2010","Customer Name":"Texas Comptroller of Public Accounts","Vendor Name":"Resource Integrators, LLC","Purchase Amount":"16320.0","Contract Number":"DIR-SDD-1285","RFO Description":"Information Technology Staff Augmentation Contract (ITSAC)","RFO Number":"DIR-SDD-TMP-141","Customer Type":"State Agency","Customer Contact":"ACCOUNTS PAYABLE","Customer Address":"111 E 17th St.","Customer City":"Austin","Customer State":"TX","Customer ZIP":"78774","Customer Geolocation":"111 E 17th St.\nAustin, TX 78774\n(30.27852082800007, -97.73818883999996)","Vendor Contact":"Audra Terrazas","Vendor HUB Type":"Woman Owned","Vendor Address":"7301 Rr620 #155 Pmb 294","Vendor City":"Austin","Vendor State":"TX","Vendor Zip":"78726","Vendor Geolocation":"7301 Rr620 #155 Pmb 294\nAustin, TX 78726\n(30.429092166000032, -97.83834971299996)","Reseller Name":"","Reseller HUB Type":"Non HUB","Reseller Address":"","Reseller City":"","Reseller State":"","Reseller Zip":"","Reseller Geolocation":"","Reseller Phone":"","Report Received Month":"2010-05-00","Purchase Month":"2010-05-00","Brand Name":"N/A","Purchase Description":"IT STAFFING SERVICES","Product Number":"STAFFING SERVICES","Order Quantity":160,"Unit Price":102,"PO Number":"30400 10-1945.","Invoice Number":"382","Order Date":"","Shipped Date":"2010-01-15T06:00:00.000Z","DIR Contract Mgr":"Joan Scott","Contract Type":"Services","Contract Subtype":"IT Staffing Services","Contract Start Date":"2009-09-01T05:00:00.000Z","Contract End Date":"2013-08-31T05:00:00.000Z","Contract Termination Date":"2013-08-31T05:00:00.000Z","Staffing Contractor Name":"VINCENT FAIL","Staffing Technology":"Applications","Staffing Title":"Developer","Staffing Level":"Developer 3","Staffing Technology Type":"Emerging","Staffing Start Date":null,"Staffing Acquistion Type":"Competitive","Sales Fact Number":8103461,"ORIG - Purchase Month":"201005","ORIG - Report Received Month":"201005","ORIG - Shipped Date":"2010-01-15T00:00:00Z","ORIG - Contract Start Date":"2009-09-01T00:00:00Z","ORIG - Contract End Date":"2013-08-31T00:00:00Z","ORIG - Contract Termination Date":"2013-08-31T00:00:00Z","ORIG - Staffing Start Date":"","Key":60853},{"Fiscal Year":"2010","Customer Name":"Health and Human Services Commission, Texas","Vendor Name":"Denovo Ventures, LLC","Purchase Amount":"8415.47","Contract Number":"DIR-SDD-1268","RFO Description":"Information Technology Staff Augmentation Contract (ITSAC)","RFO Number":"DIR-SDD-TMP-141","Customer Type":"State Agency","Customer Contact":"SHERIDAN G. CLARK","Customer Address":"Po Box 13247","Customer City":"Austin","Customer State":"TX","Customer ZIP":"78711","Customer Geolocation":"Po Box 13247\nAustin, TX 78711\n(30.278672420000078, -97.73878825699995)","Vendor Contact":"William Hylton","Vendor HUB Type":"Non HUB","Vendor Address":"4000 Barranca Parkway, Suite 250","Vendor City":"Irvine","Vendor State":"CA","Vendor Zip":"92604","Vendor Geolocation":"4000 Barranca Parkway, Suite 250\nIrvine, CA 92604\n(33.68388635900004, -117.80815566299998)","Reseller Name":"","Reseller HUB Type":"Non HUB","Reseller Address":"","Reseller City":"","Reseller State":"","Reseller Zip":"","Reseller Geolocation":"","Reseller Phone":"","Report Received Month":"2010-01-00","Purchase Month":"2010-01-00","Brand Name":"N/A","Purchase Description":"IT STAFFING SERVICES","Product Number":"STAFFING SERVICES","Order Quantity":81,"Unit Price":104.54,"PO Number":"52900-0-0000044890","Invoice Number":"13773","Order Date":"","Shipped Date":"2009-10-27T05:00:00.000Z","DIR Contract Mgr":"Aiko Neill","Contract Type":"Services","Contract Subtype":"IT Staffing Services","Contract Start Date":"2009-10-27T05:00:00.000Z","Contract End Date":"2011-10-27T05:00:00.000Z","Contract Termination Date":"2013-10-27T05:00:00.000Z","Staffing Contractor Name":"VINCENT FAIL","Staffing Technology":"Project Management","Staffing Title":"Project Lead","Staffing Level":"Project Lead 2","Staffing Technology Type":"Emerging","Staffing Start Date":null,"Staffing Acquistion Type":"Renewal","Sales Fact Number":6786213,"ORIG - Purchase Month":"201001","ORIG - Report Received Month":"201001","ORIG - Shipped Date":"2009-10-27T00:00:00Z","ORIG - Contract Start Date":"2009-10-27T00:00:00Z","ORIG - Contract End Date":"2011-10-27T00:00:00Z","ORIG - Contract Termination Date":"2013-10-27T00:00:00Z","ORIG - Staffing Start Date":"","Key":60854},{"Fiscal Year":"2010","Customer Name":"Texas Comptroller of Public Accounts","Vendor Name":"Resource Integrators, LLC","Purchase Amount":"14892.0","Contract Number":"DIR-SDD-1285","RFO Description":"Information Technology Staff Augmentation Contract (ITSAC)","RFO Number":"DIR-SDD-TMP-141","Customer Type":"State Agency","Customer Contact":"ACCOUNTS PAYABLE","Customer Address":"111 E 17th St.","Customer City":"Austin","Customer State":"TX","Customer ZIP":"78774","Customer Geolocation":"111 E 17th St.\nAustin, TX 78774\n(30.27852082800007, -97.73818883999996)","Vendor Contact":"Audra Terrazas","Vendor HUB Type":"Woman Owned","Vendor Address":"7301 Rr620 #155 Pmb 294","Vendor City":"Austin","Vendor State":"TX","Vendor Zip":"78726","Vendor Geolocation":"7301 Rr620 #155 Pmb 294\nAustin, TX 78726\n(30.429092166000032, -97.83834971299996)","Reseller Name":"","Reseller HUB Type":"Non HUB","Reseller Address":"","Reseller City":"","Reseller State":"","Reseller Zip":"","Reseller Geolocation":"","Reseller Phone":"","Report Received Month":"2010-02-00","Purchase Month":"2010-02-00","Brand Name":"N/A","Purchase Description":"IT STAFFING SERVICES","Product Number":"STAFFING SERVICES","Order Quantity":146,"Unit Price":102,"PO Number":"30400 10-1945.","Invoice Number":"3","Order Date":"","Shipped Date":"2010-01-15T06:00:00.000Z","DIR Contract Mgr":"Joan Scott","Contract Type":"Services","Contract Subtype":"IT Staffing Services","Contract Start Date":"2009-09-01T05:00:00.000Z","Contract End Date":"2013-08-31T05:00:00.000Z","Contract Termination Date":"2013-08-31T05:00:00.000Z","Staffing Contractor Name":"VINCENT FAIL","Staffing Technology":"Applications","Staffing Title":"Developer","Staffing Level":"Developer 3","Staffing Technology Type":"Emerging","Staffing Start Date":null,"Staffing Acquistion Type":"Competitive","Sales Fact Number":7184025,"ORIG - Purchase Month":"201002","ORIG - Report Received Month":"201002","ORIG - Shipped Date":"2010-01-15T00:00:00Z","ORIG - Contract Start Date":"2009-09-01T00:00:00Z","ORIG - Contract End Date":"2013-08-31T00:00:00Z","ORIG - Contract Termination Date":"2013-08-31T00:00:00Z","ORIG - Staffing Start Date":"","Key":60855},{"Fiscal Year":"2010","Customer Name":"Health and Human Services Commission, Texas","Vendor Name":"Denovo Ventures, LLC","Purchase Amount":"16465.05","Contract Number":"DIR-SDD-1268","RFO Description":"Information Technology Staff Augmentation Contract (ITSAC)","RFO Number":"DIR-SDD-TMP-141","Customer Type":"State Agency","Customer Contact":"SHERIDAN G. CLARK","Customer Address":"Po Box 13247","Customer City":"Austin","Customer State":"TX","Customer ZIP":"78711","Customer Geolocation":"Po Box 13247\nAustin, TX 78711\n(30.278672420000078, -97.73878825699995)","Vendor Contact":"William Hylton","Vendor HUB Type":"Non HUB","Vendor Address":"4000 Barranca Parkway, Suite 250","Vendor City":"Irvine","Vendor State":"CA","Vendor Zip":"92604","Vendor Geolocation":"4000 Barranca Parkway, Suite 250\nIrvine, CA 92604\n(33.68388635900004, -117.80815566299998)","Reseller Name":"","Reseller HUB Type":"Non HUB","Reseller Address":"","Reseller City":"","Reseller State":"","Reseller Zip":"","Reseller Geolocation":"","Reseller Phone":"","Report Received Month":"2009-12-00","Purchase Month":"2009-12-00","Brand Name":"N/A","Purchase Description":"IT STAFFING SERVICES","Product Number":"STAFFING SERVICES","Order Quantity":158,"Unit Price":104.54,"PO Number":"52900-0-0000044890","Invoice Number":"13724","Order Date":"","Shipped Date":"2009-10-27T05:00:00.000Z","DIR Contract Mgr":"Aiko Neill","Contract Type":"Services","Contract Subtype":"IT Staffing Services","Contract Start Date":"2009-10-27T05:00:00.000Z","Contract End Date":"2011-10-27T05:00:00.000Z","Contract Termination Date":"2013-10-27T05:00:00.000Z","Staffing Contractor Name":"VINCENT FAIL","Staffing Technology":"Project Management","Staffing Title":"Project Lead","Staffing Level":"Project Lead 2","Staffing Technology Type":"Emerging","Staffing Start Date":null,"Staffing Acquistion Type":"Renewal","Sales Fact Number":6579598,"ORIG - Purchase Month":"200912","ORIG - Report Received Month":"200912","ORIG - Shipped Date":"2009-10-27T00:00:00Z","ORIG - Contract Start Date":"2009-10-27T00:00:00Z","ORIG - Contract End Date":"2011-10-27T00:00:00Z","ORIG - Contract Termination Date":"2013-10-27T00:00:00Z","ORIG - Staffing Start Date":"","Key":60856},{"Fiscal Year":"2010","Customer Name":"Texas Comptroller of Public Accounts","Vendor Name":"Resource Integrators, LLC","Purchase Amount":"17850.0","Contract Number":"DIR-SDD-1285","RFO Description":"Information Technology Staff Augmentation Contract (ITSAC)","RFO Number":"DIR-SDD-TMP-141","Customer Type":"State Agency","Customer Contact":"ACCOUNTS PAYABLE","Customer Address":"111 E 17th St.","Customer City":"Austin","Customer State":"TX","Customer ZIP":"78774","Customer Geolocation":"111 E 17th St.\nAustin, TX 78774\n(30.27852082800007, -97.73818883999996)","Vendor Contact":"Audra Terrazas","Vendor HUB Type":"Woman Owned","Vendor Address":"7301 Rr620 #155 Pmb 294","Vendor City":"Austin","Vendor State":"TX","Vendor Zip":"78726","Vendor Geolocation":"7301 Rr620 #155 Pmb 294\nAustin, TX 78726\n(30.429092166000032, -97.83834971299996)","Reseller Name":"","Reseller HUB Type":"Non HUB","Reseller Address":"","Reseller City":"","Reseller State":"","Reseller Zip":"","Reseller Geolocation":"","Reseller Phone":"","Report Received Month":"2010-03-00","Purchase Month":"2010-03-00","Brand Name":"N/A","Purchase Description":"IT STAFFING SERVICES","Product Number":"STAFFING SERVICES","Order Quantity":175,"Unit Price":102,"PO Number":"30400 10-1945.","Invoice Number":"368","Order Date":"","Shipped Date":"2010-01-15T06:00:00.000Z","DIR Contract Mgr":"Joan Scott","Contract Type":"Services","Contract Subtype":"IT Staffing Services","Contract Start Date":"2009-09-01T05:00:00.000Z","Contract End Date":"2013-08-31T05:00:00.000Z","Contract Termination Date":"2013-08-31T05:00:00.000Z","Staffing Contractor Name":"VINCENT FAIL","Staffing Technology":"Applications","Staffing Title":"Developer","Staffing Level":"Developer 3","Staffing Technology Type":"Emerging","Staffing Start Date":null,"Staffing Acquistion Type":"Competitive","Sales Fact Number":7504144,"ORIG - Purchase Month":"201003","ORIG - Report Received Month":"201003","ORIG - Shipped Date":"2010-01-15T00:00:00Z","ORIG - Contract Start Date":"2009-09-01T00:00:00Z","ORIG - Contract End Date":"2013-08-31T00:00:00Z","ORIG - Contract Termination Date":"2013-08-31T00:00:00Z","ORIG - Staffing Start Date":"","Key":60857},{"Fiscal Year":"2010","Customer Name":"Texas Comptroller of Public Accounts","Vendor Name":"Resource Integrators, LLC","Purchase Amount":"8517.0","Contract Number":"DIR-SDD-1285","RFO Description":"Information Technology Staff Augmentation Contract (ITSAC)","RFO Number":"DIR-SDD-TMP-141","Customer Type":"State Agency","Customer Contact":"ACCOUNTS PAYABLE","Customer Address":"111 E 17th St.","Customer City":"Austin","Customer State":"TX","Customer ZIP":"78774","Customer Geolocation":"111 E 17th St.\nAustin, TX 78774\n(30.27852082800007, -97.73818883999996)","Vendor Contact":"Audra Terrazas","Vendor HUB Type":"Woman Owned","Vendor Address":"7301 Rr620 #155 Pmb 294","Vendor City":"Austin","Vendor State":"TX","Vendor Zip":"78726","Vendor Geolocation":"7301 Rr620 #155 Pmb 294\nAustin, TX 78726\n(30.429092166000032, -97.83834971299996)","Reseller Name":"","Reseller HUB Type":"Non HUB","Reseller Address":"","Reseller City":"","Reseller State":"","Reseller Zip":"","Reseller Geolocation":"","Reseller Phone":"","Report Received Month":"2010-07-00","Purchase Month":"2010-07-00","Brand Name":"N/A","Purchase Description":"IT STAFFING SERVICES","Product Number":"STAFFING SERVICES","Order Quantity":84,"Unit Price":102,"PO Number":"30400 10-1945.","Invoice Number":"395","Order Date":"","Shipped Date":"2010-01-15T06:00:00.000Z","DIR Contract Mgr":"Joan Scott","Contract Type":"Services","Contract Subtype":"IT Staffing Services","Contract Start Date":"2009-09-01T05:00:00.000Z","Contract End Date":"2013-08-31T05:00:00.000Z","Contract Termination Date":"2013-08-31T05:00:00.000Z","Staffing Contractor Name":"VINCENT FAIL","Staffing Technology":"Applications","Staffing Title":"Developer","Staffing Level":"Developer 3","Staffing Technology Type":"Emerging","Staffing Start Date":null,"Staffing Acquistion Type":"Competitive","Sales Fact Number":8676708,"ORIG - Purchase Month":"201007","ORIG - Report Received Month":"201007","ORIG - Shipped Date":"2010-01-15T00:00:00Z","ORIG - Contract Start Date":"2009-09-01T00:00:00Z","ORIG - Contract End Date":"2013-08-31T00:00:00Z","ORIG - Contract Termination Date":"2013-08-31T00:00:00Z","ORIG - Staffing Start Date":"","Key":60858},{"Fiscal Year":"2010","Customer Name":"Texas Comptroller of Public Accounts","Vendor Name":"Resource Integrators, LLC","Purchase Amount":"16779.0","Contract Number":"DIR-SDD-1285","RFO Description":"Information Technology Staff Augmentation Contract (ITSAC)","RFO Number":"DIR-SDD-TMP-141","Customer Type":"State Agency","Customer Contact":"ACCOUNTS PAYABLE","Customer Address":"111 E 17th St.","Customer City":"Austin","Customer State":"TX","Customer ZIP":"78774","Customer Geolocation":"111 E 17th St.\nAustin, TX 78774\n(30.27852082800007, -97.73818883999996)","Vendor Contact":"Audra Terrazas","Vendor HUB Type":"Woman Owned","Vendor Address":"7301 Rr620 #155 Pmb 294","Vendor City":"Austin","Vendor State":"TX","Vendor Zip":"78726","Vendor Geolocation":"7301 Rr620 #155 Pmb 294\nAustin, TX 78726\n(30.429092166000032, -97.83834971299996)","Reseller Name":"","Reseller HUB Type":"Non HUB","Reseller Address":"","Reseller City":"","Reseller State":"","Reseller Zip":"","Reseller Geolocation":"","Reseller Phone":"","Report Received Month":"2010-06-00","Purchase Month":"2010-06-00","Brand Name":"N/A","Purchase Description":"IT STAFFING SERVICES","Product Number":"STAFFING SERVICES","Order Quantity":165,"Unit Price":102,"PO Number":"30400 10-1945.","Invoice Number":"387","Order Date":"","Shipped Date":"2010-01-15T06:00:00.000Z","DIR Contract Mgr":"Joan Scott","Contract Type":"Services","Contract Subtype":"IT Staffing Services","Contract Start Date":"2009-09-01T05:00:00.000Z","Contract End Date":"2013-08-31T05:00:00.000Z","Contract Termination Date":"2013-08-31T05:00:00.000Z","Staffing Contractor Name":"VINCENT FAIL","Staffing Technology":"Applications","Staffing Title":"Developer","Staffing Level":"Developer 3","Staffing Technology Type":"Emerging","Staffing Start Date":null,"Staffing Acquistion Type":"Competitive","Sales Fact Number":8393915,"ORIG - Purchase Month":"201006","ORIG - Report Received Month":"201006","ORIG - Shipped Date":"2010-01-15T00:00:00Z","ORIG - Contract Start Date":"2009-09-01T00:00:00Z","ORIG - Contract End Date":"2013-08-31T00:00:00Z","ORIG - Contract Termination Date":"2013-08-31T00:00:00Z","ORIG - Staffing Start Date":"","Key":60859},{"Fiscal Year":"2010","Customer Name":"Texas Comptroller of Public Accounts","Vendor Name":"Resource Integrators, LLC","Purchase Amount":"16473.0","Contract Number":"DIR-SDD-1285","RFO Description":"Information Technology Staff Augmentation Contract (ITSAC)","RFO Number":"DIR-SDD-TMP-141","Customer Type":"State Agency","Customer Contact":"ACCOUNTS PAYABLE","Customer Address":"111 E 17th St.","Customer City":"Austin","Customer State":"TX","Customer ZIP":"78774","Customer Geolocation":"111 E 17th St.\nAustin, TX 78774\n(30.27852082800007, -97.73818883999996)","Vendor Contact":"Audra Terrazas","Vendor HUB Type":"Woman Owned","Vendor Address":"7301 Rr620 #155 Pmb 294","Vendor City":"Austin","Vendor State":"TX","Vendor Zip":"78726","Vendor Geolocation":"7301 Rr620 #155 Pmb 294\nAustin, TX 78726\n(30.429092166000032, -97.83834971299996)","Reseller Name":"","Reseller HUB Type":"Non HUB","Reseller Address":"","Reseller City":"","Reseller State":"","Reseller Zip":"","Reseller Geolocation":"","Reseller Phone":"","Report Received Month":"2010-04-00","Purchase Month":"2010-04-00","Brand Name":"N/A","Purchase Description":"IT STAFFING SERVICES","Product Number":"STAFFING SERVICES","Order Quantity":162,"Unit Price":102,"PO Number":"30400 10-1945.","Invoice Number":"375","Order Date":"","Shipped Date":"2010-01-15T06:00:00.000Z","DIR Contract Mgr":"Joan Scott","Contract Type":"Services","Contract Subtype":"IT Staffing Services","Contract Start Date":"2009-09-01T05:00:00.000Z","Contract End Date":"2013-08-31T05:00:00.000Z","Contract Termination Date":"2013-08-31T05:00:00.000Z","Staffing Contractor Name":"VINCENT FAIL","Staffing Technology":"Applications","Staffing Title":"Developer","Staffing Level":"Developer 3","Staffing Technology Type":"Emerging","Staffing Start Date":null,"Staffing Acquistion Type":"Competitive","Sales Fact Number":7785168,"ORIG - Purchase Month":"201004","ORIG - Report Received Month":"201004","ORIG - Shipped Date":"2010-01-15T00:00:00Z","ORIG - Contract Start Date":"2009-09-01T00:00:00Z","ORIG - Contract End Date":"2013-08-31T00:00:00Z","ORIG - Contract Termination Date":"2013-08-31T00:00:00Z","ORIG - Staffing Start Date":"","Key":60860},{"Fiscal Year":"2010","Customer Name":"Texas Comptroller of Public Accounts","Vendor Name":"Resource Integrators, LLC","Purchase Amount":"3264.0","Contract Number":"DIR-SDD-1285","RFO Description":"Information Technology Staff Augmentation Contract (ITSAC)","RFO Number":"DIR-SDD-TMP-141","Customer Type":"State Agency","Customer Contact":"ACCOUNTS PAYABLE","Customer Address":"111 E 17th St.","Customer City":"Austin","Customer State":"TX","Customer ZIP":"78774","Customer Geolocation":"111 E 17th St.\nAustin, TX 78774\n(30.27852082800007, -97.73818883999996)","Vendor Contact":"Audra Terrazas","Vendor HUB Type":"Woman Owned","Vendor Address":"7301 Rr620 #155 Pmb 294","Vendor City":"Austin","Vendor State":"TX","Vendor Zip":"78726","Vendor Geolocation":"7301 Rr620 #155 Pmb 294\nAustin, TX 78726\n(30.429092166000032, -97.83834971299996)","Reseller Name":"","Reseller HUB Type":"Non HUB","Reseller Address":"","Reseller City":"","Reseller State":"","Reseller Zip":"","Reseller Geolocation":"","Reseller Phone":"","Report Received Month":"2010-01-00","Purchase Month":"2010-01-00","Brand Name":"N/A","Purchase Description":"IT STAFFING SERVICES","Product Number":"STAFFING SERVICES","Order Quantity":32,"Unit Price":102,"PO Number":"30400 10-1945.","Invoice Number":"357","Order Date":"","Shipped Date":"2010-01-15T06:00:00.000Z","DIR Contract Mgr":"Joan Scott","Contract Type":"Services","Contract Subtype":"IT Staffing Services","Contract Start Date":"2009-09-01T05:00:00.000Z","Contract End Date":"2013-08-31T05:00:00.000Z","Contract Termination Date":"2013-08-31T05:00:00.000Z","Staffing Contractor Name":"VINCENT FAIL","Staffing Technology":"Applications","Staffing Title":"Developer","Staffing Level":"Developer 3","Staffing Technology Type":"Emerging","Staffing Start Date":null,"Staffing Acquistion Type":"Competitive","Sales Fact Number":6786705,"ORIG - Purchase Month":"201001","ORIG - Report Received Month":"201001","ORIG - Shipped Date":"2010-01-15T00:00:00Z","ORIG - Contract Start Date":"2009-09-01T00:00:00Z","ORIG - Contract End Date":"2013-08-31T00:00:00Z","ORIG - Contract Termination Date":"2013-08-31T00:00:00Z","ORIG - Staffing Start Date":"","Key":60861},{"Fiscal Year":"2010","Customer Name":"Health and Human Services Commission, Texas","Vendor Name":"Denovo Ventures, LLC","Purchase Amount":"13172.04","Contract Number":"DIR-SDD-1268","RFO Description":"Information Technology Staff Augmentation Contract (ITSAC)","RFO Number":"DIR-SDD-TMP-141","Customer Type":"State Agency","Customer Contact":"SHERIDAN G. CLARK","Customer Address":"Po Box 13247","Customer City":"Austin","Customer State":"TX","Customer ZIP":"78711","Customer Geolocation":"Po Box 13247\nAustin, TX 78711\n(30.278672420000078, -97.73878825699995)","Vendor Contact":"William Hylton","Vendor HUB Type":"Non HUB","Vendor Address":"4000 Barranca Parkway, Suite 250","Vendor City":"Irvine","Vendor State":"CA","Vendor Zip":"92604","Vendor Geolocation":"4000 Barranca Parkway, Suite 250\nIrvine, CA 92604\n(33.68388635900004, -117.80815566299998)","Reseller Name":"","Reseller HUB Type":"Non HUB","Reseller Address":"","Reseller City":"","Reseller State":"","Reseller Zip":"","Reseller Geolocation":"","Reseller Phone":"","Report Received Month":"2009-11-00","Purchase Month":"2009-11-00","Brand Name":"N/A","Purchase Description":"IT STAFFING SERVICES","Product Number":"STAFFING SERVICES","Order Quantity":126,"Unit Price":104.54,"PO Number":"52900-0-0000044890","Invoice Number":"13670","Order Date":"","Shipped Date":"2009-10-27T05:00:00.000Z","DIR Contract Mgr":"Aiko Neill","Contract Type":"Services","Contract Subtype":"IT Staffing Services","Contract Start Date":"2009-10-27T05:00:00.000Z","Contract End Date":"2011-10-27T05:00:00.000Z","Contract Termination Date":"2013-10-27T05:00:00.000Z","Staffing Contractor Name":"VINCENT FAIL","Staffing Technology":"Project Management","Staffing Title":"Project Lead","Staffing Level":"Project Lead 2","Staffing Technology Type":"Emerging","Staffing Start Date":null,"Staffing Acquistion Type":"Renewal","Sales Fact Number":6576321,"ORIG - Purchase Month":"200911","ORIG - Report Received Month":"200911","ORIG - Shipped Date":"2009-10-27T00:00:00Z","ORIG - Contract Start Date":"2009-10-27T00:00:00Z","ORIG - Contract End Date":"2011-10-27T00:00:00Z","ORIG - Contract Termination Date":"2013-10-27T00:00:00Z","ORIG - Staffing Start Date":"","Key":60862}]